blackspammerbd/__init__.py
blackspammerbd/core.py
blackspammerbd1/__init__.py
blackspammerbd1/server.py
blackspammerbd_one/__init__.py
blackspammerbd_one/cli.py
blackspammerbd_one-1.0.0.dist-info/LICENSE.chromedriver
blackspammerbd_one-1.0.0.dist-info/METADATA
blackspammerbd_one-1.0.0.dist-info/WHEEL
blackspammerbd_one-1.0.0.dist-info/entry_points.txt
blackspammerbd_one-1.0.0.dist-info/top_level.txt
blackspammerbd_one-1.0.0.dist-info/RECORD
