Metadata-Version: 2.2
Name: blackspammerbd_one
Version: 1.0.0
Summary: CLI package for device connection and file transfer
Home-page: https://github.com/yourusername/blackspammerbd_one
Author: Shawpon Sp
Author-email: shawponsp6@gmail.com
Classifier: Programming Language :: Python :: 3
Classifier: Operating System :: OS Independent
License-File: LICENSE.chromedriver
Requires-Dist: colorama
Dynamic: author
Dynamic: author-email
Dynamic: classifier
Dynamic: home-page
Dynamic: requires-dist
Dynamic: summary
